{
  "eyebrow": "Trusted Residential Care",
  "headline": "Compassionate Residential Care You Can Trust",
  "subheadline": "Providing safe and supportive residential care for seniors and adults who need assistance with daily living in a warm, home-like environment.",
  "primaryCTA": { "label": "Schedule a Tour", "href": "/schedule-a-tour" },
  "secondaryCTA": { "label": "Explore Our Homes", "href": "/our-homes" },
  "heroImage": "https://images.unsplash.com/photo-1586023492125-27b2c045efd7?w=1200&h=800&auto=format&fit=crop&q=80",
  "heroImageAlt": "Warm and welcoming living room at Capricorn Group Care"
}
